<?xml version='1.0' encoding='utf-8'?>
<annotation><size><width>640</width><height>512</height><depth>1</depth></size><segmented>0</segmented><object><name>person</name><pose>Unspecified</pose><truncated>0</truncated><difficult>0</difficult><point><x>364.19355999280435</x><y>411.0192480661989</y></point></object><object><name>person</name><pose>Unspecified</pose><truncated>0</truncated><difficult>0</difficult><point><x>486.6155783414282</x><y>403.97337650656596</y></point></object><object><name>person</name><pose>Unspecified</pose><truncated>0</truncated><difficult>0</difficult><point><x>885.5880554056483</x><y>753.6247526533548</y></point></object><object><name>person</name><pose>Unspecified</pose><truncated>0</truncated><difficult>0</difficult><point><x>575.569706781795</x><y>305.3311746717035</y></point></object><object><name>person</name><pose>Unspecified</pose><truncated>0</truncated><difficult>0</difficult><point><x>586.1385141212446</x><y>204.04677100197875</y></point></object><object><name>person</name><pose>Unspecified</pose><truncated>0</truncated><difficult>0</difficult><point><x>718.2486058643639</x><y>315.89998201115304</y></point></object><object><name>person</name><pose>Unspecified</pose><truncated>0</truncated><difficult>0</difficult><point><x>779.0192480661988</x><y>307.09264256161174</y></point></object><object><name>person</name><pose>Unspecified</pose><truncated>0</truncated><difficult>0</difficult><point><x>788.7073214606942</x><y>274.50548659830895</y></point></object><object><name>person</name><pose>Unspecified</pose><truncated>0</truncated><difficult>0</difficult><point><x>467.2394315524373</x><y>209.3311746717035</y></point></object><object><name>person</name><pose>Unspecified</pose><truncated>0</truncated><difficult>0</difficult><point><x>387.9733765065657</x><y>166.17521136895118</y></point></object><object><name>person</name><pose>Unspecified</pose><truncated>0</truncated><difficult>0</difficult><point><x>337.7715416441805</x><y>222.54218384601546</y></point></object><object><name>person</name><pose>Unspecified</pose><truncated>0</truncated><difficult>0</difficult><point><x>98.21190861665762</x><y>139.75319302032736</y></point></object><object><name>person</name><pose>Unspecified</pose><truncated>0</truncated><difficult>0</difficult><point><x>869.734844396474</x><y>135.34952329555674</y></point></object><object><name>person</name><pose>Unspecified</pose><truncated>0</truncated><difficult>0</difficult><point><x>890.8724590753731</x><y>151.20273430473105</y></point></object><object><name>person</name><pose>Unspecified</pose><truncated>0</truncated><difficult>0</difficult><point><x>949.0008994423456</x><y>120.37704623133651</y></point></object><object><name>person</name><pose>Unspecified</pose><truncated>0</truncated><difficult>0</difficult><point><x>986.8724590753731</x><y>104.52383522216219</y></point></object><object><name>person</name><pose>Unspecified</pose><truncated>0</truncated><difficult>0</difficult><point><x>978.0651196258317</x><y>75.45961503867603</y></point></object><object><name>person</name><pose>Unspecified</pose><truncated>0</truncated><difficult>0</difficult><point><x>923.4596150386758</x><y>71.05594531390543</y></point></object><object><name>person</name><pose>Unspecified</pose><truncated>0</truncated><difficult>0</difficult><point><x>917.2944774239969</x><y>89.55135815794205</y></point></object><object><name>person</name><pose>Unspecified</pose><truncated>0</truncated><difficult>0</difficult><point><x>889.991725130419</x><y>71.93667925885943</y></point></object><object><name>person</name><pose>Unspecified</pose><truncated>0</truncated><difficult>0</difficult><point><x>852.1201654973914</x><y>77.2210829285842</y></point></object><object><name>person</name><pose>Unspecified</pose><truncated>0</truncated><difficult>0</difficult><point><x>816.8908076992263</x><y>73.69814714876775</y></point></object><object><name>person</name><pose>Unspecified</pose><truncated>0</truncated><difficult>0</difficult><point><x>762.2853031120703</x><y>77.2210829285842</y></point></object><object><name>person</name><pose>Unspecified</pose><truncated>0</truncated><difficult>0</difficult><point><x>744.6706242129877</x><y>73.69814714876775</y></point></object><object><name>person</name><pose>Unspecified</pose><truncated>0</truncated><difficult>0</difficult><point><x>698.8724590753732</x><y>67.5330095340888</y></point></object><object><name>person</name><pose>Unspecified</pose><truncated>0</truncated><difficult>0</difficult><point><x>637.221082928584</x><y>86.02842237812557</y></point></object><object><name>person</name><pose>Unspecified</pose><truncated>0</truncated><difficult>0</difficult><point><x>491.0192480661988</x><y>83.38622054326312</y></point></object><object><name>person</name><pose>Unspecified</pose><truncated>0</truncated><difficult>0</difficult><point><x>463.7164957726208</x><y>79.86328476344666</y></point></object><object><name>person</name><pose>Unspecified</pose><truncated>0</truncated><difficult>0</difficult><point><x>19.606404029501686</x><y>72.92750494693293</y></point></object><object><name>person</name><pose>Unspecified</pose><truncated>0</truncated><difficult>0</difficult><point><x>86.54218384601542</x><y>31.092642561611843</y></point></object><object><name>person</name><pose>Unspecified</pose><truncated>0</truncated><difficult>0</difficult><point><x>48.23025724051084</x><y>24.92750494693292</y></point></object><object><name>person</name><pose>Unspecified</pose><truncated>0</truncated><difficult>0</difficult><point><x>8.120165497391616</x><y>13.643101277208153</y></point></object><object><name>person</name><pose>Unspecified</pose><truncated>0</truncated><difficult>0</difficult><point><x>246.505486598309</x><y>42.156862745098046</y></point></object><object><name>person</name><pose>Unspecified</pose><truncated>0</truncated><difficult>0</difficult><point><x>294.2853031120705</x><y>41.71649577262098</y></point></object><object><name>person</name><pose>Unspecified</pose><truncated>0</truncated><difficult>0</difficult><point><x>297.58805540564845</x><y>26.744018708400805</y></point></object><object><name>person</name><pose>Unspecified</pose><truncated>0</truncated><difficult>0</difficult><point><x>354.945853570786</x><y>45.239431552437516</y></point></object><object><name>person</name><pose>Unspecified</pose><truncated>0</truncated><difficult>0</difficult><point><x>319.7164957726209</x><y>54.707321460694395</y></point></object><object><name>person</name><pose>Unspecified</pose><truncated>0</truncated><difficult>0</difficult><point><x>388.413743479043</x><y>41.38622054326319</y></point></object><object><name>person</name><pose>Unspecified</pose><truncated>0</truncated><difficult>0</difficult><point><x>397.11099118546497</x><y>37.092642561611825</y></point></object><object><name>person</name><pose>Unspecified</pose><truncated>0</truncated><difficult>0</difficult><point><x>409.8816333872998</x><y>47.441266414822834</y></point></object><object><name>person</name><pose>Unspecified</pose><truncated>0</truncated><difficult>0</difficult><point><x>424.74401870840063</x><y>74.46878935060265</y></point></object><object><name>person</name><pose>Unspecified</pose><truncated>0</truncated><difficult>0</difficult><point><x>439.7164957726208</x><y>31.753193020327423</y></point></object><object><name>person</name><pose>Unspecified</pose><truncated>0</truncated><difficult>0</difficult><point><x>472.3036517359236</x><y>26.248605864364116</y></point></object><object><name>person</name><pose>Unspecified</pose><truncated>0</truncated><difficult>0</difficult><point><x>474.5054865983089</x><y>35.716495772620995</y></point></object><object><name>person</name><pose>Unspecified</pose><truncated>0</truncated><difficult>0</difficult><point><x>263.34952329555665</x><y>155.716495772621</y></point></object><object><name>person</name><pose>Unspecified</pose><truncated>0</truncated><difficult>0</difficult><point><x>499.3862205432631</x><y>71.44126641482282</y></point></object><object><name>person</name><pose>Unspecified</pose><truncated>0</truncated><difficult>0</difficult><point><x>514.4687893506025</x><y>46.89080769922649</y></point></object><object><name>person</name><pose>Unspecified</pose><truncated>0</truncated><difficult>0</difficult><point><x>535.3862205432631</x><y>47.11099118546502</y></point></object><object><name>person</name><pose>Unspecified</pose><truncated>0</truncated><difficult>0</difficult><point><x>542.6522755891347</x><y>57.89998201115309</y></point></object><object><name>person</name><pose>Unspecified</pose><truncated>0</truncated><difficult>0</difficult><point><x>537.3678719194099</x><y>21.01924806619897</y></point></object><object><name>person</name><pose>Unspecified</pose><truncated>0</truncated><difficult>0</difficult><point><x>553.0008994423456</x><y>28.725670084547595</y></point></object><object><name>person</name><pose>Unspecified</pose><truncated>0</truncated><difficult>0</difficult><point><x>533.294477423997</x><y>93.62475265335495</y></point></object><object><name>person</name><pose>Unspecified</pose><truncated>0</truncated><difficult>0</difficult><point><x>628.0834682496851</x><y>48.54218384601548</y></point></object><object><name>person</name><pose>Unspecified</pose><truncated>0</truncated><difficult>0</difficult><point><x>648.1201654973914</x><y>42.156862745098046</y></point></object><object><name>person</name><pose>Unspecified</pose><truncated>0</truncated><difficult>0</difficult><point><x>598.688972836841</x><y>7.175211368951249</y></point></object><object><name>person</name><pose>Unspecified</pose><truncated>0</truncated><difficult>0</difficult><point><x>616.3036517359236</x><y>12.294477423997126</y></point></object><object><name>person</name><pose>Unspecified</pose><truncated>0</truncated><difficult>0</difficult><point><x>628.3586976074832</x><y>8.441266414822813</y></point></object><object><name>person</name><pose>Unspecified</pose><truncated>0</truncated><difficult>0</difficult><point><x>706.9642021946393</x><y>63.84493613959346</y></point></object><object><name>person</name><pose>Unspecified</pose><truncated>0</truncated><difficult>0</difficult><point><x>687.6981471487677</x><y>37.86328476344668</y></point></object><object><name>person</name><pose>Unspecified</pose><truncated>0</truncated><difficult>0</difficult><point><x>699.5880554056483</x><y>36.101816873538425</y></point></object><object><name>person</name><pose>Unspecified</pose><truncated>0</truncated><difficult>0</difficult><point><x>658.3311746717036</x><y>3.528422378125559</y></point></object><object><name>person</name><pose>Unspecified</pose><truncated>0</truncated><difficult>0</difficult><point><x>646.9091563230797</x><y>2.565119625831977</y></point></object><object><name>person</name><pose>Unspecified</pose><truncated>0</truncated><difficult>0</difficult><point><x>767.4045691671167</x><y>54.2119086166577</y></point></object><object><name>person</name><pose>Unspecified</pose><truncated>0</truncated><difficult>0</difficult><point><x>780.1752113689516</x><y>36.37704623133656</y></point></object><object><name>person</name><pose>Unspecified</pose><truncated>0</truncated><difficult>0</difficult><point><x>832.1385141212454</x><y>36.37704623133656</y></point></object><object><name>person</name><pose>Unspecified</pose><truncated>0</truncated><difficult>0</difficult><point><x>840.7256700845481</x><y>45.624752653354925</y></point></object><object><name>person</name><pose>Unspecified</pose><truncated>0</truncated><difficult>0</difficult><point><x>847.1109911854655</x><y>37.037596690052155</y></point></object><object><name>person</name><pose>Unspecified</pose><truncated>0</truncated><difficult>0</difficult><point><x>864.7256700845481</x><y>50.468789350602634</y></point></object><object><name>person</name><pose>Unspecified</pose><truncated>0</truncated><difficult>0</difficult><point><x>921.5330095340895</x><y>41.000899442345734</y></point></object><object><name>person</name><pose>Unspecified</pose><truncated>0</truncated><difficult>0</difficult><point><x>931.5330095340888</x><y>14.413743479043</y></point></object><object><name>person</name><pose>Unspecified</pose><truncated>0</truncated><difficult>0</difficult><point><x>923.716495772621</x><y>9.019248066198962</y></point></object><object><name>person</name><pose>Unspecified</pose><truncated>0</truncated><difficult>0</difficult><point><x>1020.2669544882174</x><y>31.36787191940998</y></point></object><object><name>person</name><pose>Unspecified</pose><truncated>0</truncated><difficult>0</difficult><point><x>191.56970678179522</x><y>1.4779636625291246</y></point></object><object><name>person</name><pose>Unspecified</pose><truncated>0</truncated><difficult>0</difficult><point><x>989.5146609102354</x><y>6.762367332253894</y></point></object></annotation>